LICENSE.txt
MANIFEST.in
README.md
requirements.txt
setup.py
cmaputil/__init__.py
cmaputil/cmaputil.py
cmaputil/cvdutil.py
cmaputil.egg-info/PKG-INFO
cmaputil.egg-info/SOURCES.txt
cmaputil.egg-info/dependency_links.txt
cmaputil.egg-info/requires.txt
cmaputil.egg-info/top_level.txt
colormaps/cividis.lut
colormaps/cividis.txt
colormaps/cividisHexValues.txt
colormaps/cividis_COMSOL.txt
test/test_cdpsPlots.py
test/test_optimizeMap.py
test/test_simCVD.py