Metadata-Version: 1.0
Name: cmaputil
Version: 1.2
Summary: Colormap analysis module
Home-page: https://github.com/pnnl/cmaputil
Author: Jamie R. Nunez
Author-email: jamie.nunez@pnnl.gov
License: Copyright (c) 2017, Battelle Memorial Institute
